tests/__init__.py
tests/test_object_def.py
tests/test_subscriptableclass_approach.py
tests/test_tuple_approach.py
tests/test_validate.py
typed_pyspark/__init__.py
typed_pyspark/mypy_plugin.py
typed_pyspark-0.0.5.dist-info/LICENSE.txt
typed_pyspark-0.0.5.dist-info/METADATA
typed_pyspark-0.0.5.dist-info/WHEEL
typed_pyspark-0.0.5.dist-info/top_level.txt
typed_pyspark-0.0.5.dist-info/RECORD
