Metadata-Version: 2.1
Name: typed-pyspark
Version: 0.0.5
Summary: Contains a set of abstractions to type annotate and validate dataframes in pyspark
Home-page: https://github.com/getyourguide/TypedPyspark
Author: Jean Carlo Machado
Author-email: engineering.data-products@getyourguide.com
License: UNKNOWN
Platform: UNKNOWN
License-File: LICENSE.txt
